vibrance/__init__.py
vibrance/interface.py
vibrance/manager.py
vibrance/client/__init__.py
vibrance/client/__main__.py
vibrance/controller/__init__.py
vibrance/controller/controller.py
vibrance/controller/tolerant_socket.py
vibrance/driver/__init__.py
vibrance/driver/driver.py
vibrance/driver/keypad.py
vibrance/driver/midi.py
vibrance/driver/pipe.py
vibrance/driver/pygame_if.py
vibrance/driver/uart.py
vibrance/gui/__init__.py
vibrance/gui/__main__.py
vibrance/relay/__init__.py
vibrance/relay/__main__.py
vibrance/relay/appserver.py
vibrance/relay/controlserver.py
vibrance/util/__init__.py
vibrance/util/midi_composer.py
vibrance-0.1.0.dist-info/LICENSE
vibrance-0.1.0.dist-info/METADATA
vibrance-0.1.0.dist-info/WHEEL
vibrance-0.1.0.dist-info/top_level.txt
vibrance-0.1.0.dist-info/RECORD
