Metadata-Version: 2.1
Name: vibrance
Version: 0.1.0
Summary: Crowd-based concert lighting system
Home-page: https://github.com/Breq16/vibrance
Author: Wesley Chalmers
Author-email: breq@breq.dev
License: MIT
Platform: UNKNOWN
Classifier: Programming Language :: Python :: 3 :: Only
Classifier: License :: OSI Approved :: MIT License
Classifier: Operating System :: OS Independent
Classifier: Development Status :: 2 - Pre-Alpha
Requires-Python: >=3.6
Provides-Extra: gui
Requires-Dist: flask ; extra == 'gui'
Provides-Extra: midi
Requires-Dist: mido ; extra == 'midi'
Provides-Extra: pygame
Requires-Dist: pygame ; extra == 'pygame'
Provides-Extra: relay
Requires-Dist: websockify ; extra == 'relay'
Provides-Extra: uart
Requires-Dist: pyserial ; extra == 'uart'
